pyteslable/TeslaBLE.py
pyteslable/VCSEC_pb2.py
pyteslable/__init__.py
pyteslable-0.1.4.dist-info/METADATA
pyteslable-0.1.4.dist-info/WHEEL
pyteslable-0.1.4.dist-info/top_level.txt
pyteslable-0.1.4.dist-info/RECORD
