Metadata-Version: 2.1
Name: pyteslable
Version: 0.1.4
Summary: Python interface for connecting to Tesla vehicles directly using the BLE API
Home-page: https://github.com/kaedenbrinkman/PyTeslaBLE
Author: Kaeden Brinkman
Author-email: kaeden@kaedenb.org
License: BSD 2-clause
Classifier: Development Status :: 1 - Planning
Classifier: Intended Audience :: Science/Research
Classifier: License :: OSI Approved :: BSD License
Classifier: Operating System :: POSIX :: Linux
Classifier: Operating System :: Microsoft :: Windows :: Windows 10
Classifier: Programming Language :: Python :: 3
Classifier: Programming Language :: Python :: 3.4
Classifier: Programming Language :: Python :: 3.5
Requires-Dist: simplepyble
Requires-Dist: cryptography
Requires-Dist: protobuf
